tests/test_html/__init__.py
tests/test_html/test_base.py
tests/test_html/test_episode.py
tests/test_html/test_transcript.py
tests/test_models/__init__.py
tests/test_models/test_episode.py
tests/test_models/test_transcript.py
thisamericanlife/__init__.py
thisamericanlife/client.py
thisamericanlife/endpoints.py
thisamericanlife/http.py
thisamericanlife/html/__init__.py
thisamericanlife/html/base.py
thisamericanlife/html/episode.py
thisamericanlife/html/transcript.py
thisamericanlife/models/__init__.py
thisamericanlife/models/basemodel.py
thisamericanlife/models/episode.py
thisamericanlife/models/transcript.py
thisamericanlife/utils/__init__.py
thisamericanlife/utils/tests.py
this_american_life-0.3.0.dist-info/LICENSE
this_american_life-0.3.0.dist-info/METADATA
this_american_life-0.3.0.dist-info/WHEEL
this_american_life-0.3.0.dist-info/top_level.txt
this_american_life-0.3.0.dist-info/RECORD
