Metadata-Version: 2.1
Name: this-american-life
Version: 0.3.0
Summary: scraper client for the This American Life website
Home-page: https://github.com/{package_name}
Author-email: howley.robert@gmail.com
License: UNKNOWN
Platform: UNKNOWN
Requires-Python: >=3.6.0
Requires-Dist: lxml
Requires-Dist: requests
